MANIFEST.in
README.md
requirements.txt
setup.py
rate_limit.egg-info/PKG-INFO
rate_limit.egg-info/SOURCES.txt
rate_limit.egg-info/dependency_links.txt
rate_limit.egg-info/requires.txt
rate_limit.egg-info/top_level.txt
ratelimit/__init__.py
ratelimit/decorators.py
ratelimit/base/__init__.py
ratelimit/base/base_decorators.py
ratelimit/base/constants.py
ratelimit/base/errors.py
ratelimit/base/tools.py
ratelimit/handles/__init__.py
ratelimit/handles/base.py
ratelimit/handles/discard_handle.py
ratelimit/handles/queue_handle.py
ratelimit/handles/retry_handle.py
ratelimit/limits/__init__.py
ratelimit/limits/redis_limit.py
ratelimit/queue_tools/__init__.py
ratelimit/queue_tools/base.py
ratelimit/queue_tools/local_queue.py
ratelimit/queue_tools/redis_queue.py
ratelimit/utils/__init__.py
ratelimit/utils/over_limit_handle.py