Metadata-Version: 2.1
Name: rate-limit
Version: 0.0.4
Summary: distributed rate limiter
Home-page: https://github.com/yprocfly/rate-limit
Author: Yang Peng
Author-email: yp_rocfly@foxmail.com
License: UNKNOWN
Keywords: rate,rate-limit,limit,redis-cell
Platform: UNKNOWN
Classifier: Programming Language :: Python :: 3
Classifier: Programming Language :: Python :: 3.6
